laser_util_api/__init__.py
laser_util_api/_body_workspace.py
laser_util_api/_client_interface.py
laser_util_api/_common.py
laser_util_api/_etch_item.py
laser_util_api/_item_factory.py
laser_util_api/_loop_workspace.py
laser_util_api/_project_items.py
laser_util_api/_work_settings.py
laser_util_api/client.py
laser_util_api/vector.py
laser_util_api-0.2.1.dist-info/LICENSE
laser_util_api-0.2.1.dist-info/METADATA
laser_util_api-0.2.1.dist-info/WHEEL
laser_util_api-0.2.1.dist-info/top_level.txt
laser_util_api-0.2.1.dist-info/RECORD
