Metadata-Version: 2.1
Name: laser-util-api
Version: 0.2.1
Summary: A simple Python API for the Laser Utility project
Author-email: Matt Jarvis <mattj23@gmail.com>
License: MIT License
Project-URL: Homepage, https://github.com/mattj23/laser-util-api
Project-URL: Repository, https://github.com/mattj23/laser-util-api.git
Requires-Python: >=3.9
License-File: LICENSE
Requires-Dist: numpy ~=2.0.1
Requires-Dist: jsonrpcclient ~=4.0.3
